alchemist_stack/__init__.py
alchemist_stack/context/__init__.py
alchemist_stack/context/context.py
alchemist_stack/repository/__init__.py
alchemist_stack/repository/models/__init__.py
alchemist_stack/repository/models/autotable/__init__.py
alchemist_stack/utils/__init__.py
alchemist_stack-0.1.0.dev1.dist-info/LICENSE.txt
alchemist_stack-0.1.0.dev1.dist-info/METADATA
alchemist_stack-0.1.0.dev1.dist-info/RECORD
alchemist_stack-0.1.0.dev1.dist-info/WHEEL
alchemist_stack-0.1.0.dev1.dist-info/top_level.txt
tests/context/__init__.py
tests/utils/__init__.py
