Metadata-Version: 2.1
Name: alchemist-stack
Version: 0.1.0.dev1
Summary: A Thread-Safe, Multi-Session/Multi-Connection Model-Repository-Context base for SQL Alchemy
Home-page: https://github.com/mcculloh213/alchemist-stack
Author: H.D. "Chip" McCullough IV
Author-email: hdmccullough.work@gmail.com
License: MIT
Project-URL: Documentation, https://github.com/mcculloh213/alchemist-stack
Project-URL: Source, https://github.com/mcculloh213/alchemist-stack
Project-URL: Issue Tracker, https://github.com/mcculloh213/alchemist-stack/issues
Keywords: sqlalchemy databases
Platform: UNKNOWN
Classifier: Development Status :: 2 - Pre-Alpha
Classifier: Intended Audience :: Developers
Classifier: Topic :: Database
Classifier: Topic :: Database :: Database Engines/Servers
Classifier: Topic :: Software Development :: Libraries :: Python Modules
Classifier: License :: OSI Approved :: MIT License
Classifier: Programming Language :: Python :: 3
Classifier: Programming Language :: Python :: 3.6
Requires-Python: >=3
Requires-Dist: sqlalchemy
